aquilo/__init__.py
aquilo/main.py
aquilo/browser/__init__.py
aquilo/browser/elements/__init__.py
aquilo/browser/elements/element.py
aquilo/browser/elements/typography.py
aquilo/browser/elements/containers/__init__.py
aquilo/browser/elements/containers/div.py
aquilo/html/__init__.py
aquilo/html/generators.py
aquilo/http/__init__.py
aquilo/http/wsgi.py
aquilo/management/__init__.py
aquilo/utils/__init__.py
aquilo-0.0.1.dist-info/AUTHORS
aquilo-0.0.1.dist-info/LICENSE
aquilo-0.0.1.dist-info/METADATA
aquilo-0.0.1.dist-info/WHEEL
aquilo-0.0.1.dist-info/entry_points.txt
aquilo-0.0.1.dist-info/top_level.txt
aquilo-0.0.1.dist-info/RECORD
