Metadata-Version: 2.1
Name: aquilo
Version: 0.0.1
Summary: Web framework for pythoneers
Author-email: samkelokgosiemang100@gmail.com
License: GNU General Public License v3.0
Project-URL: github, https://github.com/KeloDraken/aquilo
Requires-Python: >=3.8.10
License-File: LICENSE
License-File: AUTHORS
Requires-Dist: black
